Vlsi/Behavrioural/ST1/fa32bit.v
	module rtlfa32_4(s, cout, a, b, cin, clk);
		input [31:0] a,b;
		input cin, clk;
		output reg cout;
		output [31:0] s;
		reg [5:0] a1, a2, b1, b2, a22, b22, s1, s11, s111, s1111, s11111, s111111, s2, s22, s222, s2222, s22222, s1111111, s222222;
		reg [3:0] a3, a4, b3, b4, a33, a44, a333, a444, a4444, b333, b33, b44, b444, b4444;
		reg [3:0] s3, s33, s333, s3333, s4, s44, s4444, s33333, s444;
		reg c1, c2, c3, c4, c5, c6, ci;
		reg[3:0] a5,a55,a555,a5555,a55555,b5,b55,b555,b5555,b55555,s5,s55,s555;
		reg[3:0] a6,a66,a666,a6666,a66666,a666666,b6,b66,b666,b6666,b66666,b666666,s6,s66;
		reg[3:0] a7,a77,a777,a7777,a77777,a777777,a7777777,b7,b77,b777,b7777,b77777,b777777,b7777777,s7;


		always @ (posedge clk)
		        begin
		                a1<={a[5:0]};
		                a2<={a[11:6]};
		                a3<={a[15:12]};
		                a4<={a[19:16]};
		                a5<={a[23:20]};
				a6<={a[27:24]};
				a7<={a[31:28]};


		                b1<={b[5:0]};
		                b2<={b[11:6]};
		                b3<={b[15:12]};
		                b4<={b[19:16]};
		                b5<={b[23:20]};
				b6<={b[27:24]};
				b7<={b[31:28]};
		                ci<=cin;

		        end
		always @ (posedge clk)
		        begin
		          {c1,s1}<=a1+b1+ci;
		          a22<=a2;
			  b22<=b2;

		          a33<=a3;
		          a44<=a4;
		          b33<=b3;
		          b44<=b4;

		          a55<=a5;
		          b55<=b5;
			  a66<=a6;
		          b66<=b6;
			  
			  a77<=a7;
			  b77<=b7;


		        end
		always @ (posedge clk)
		        begin
		          s11<=s1;
		          {c2,s2}<=a22+b22+c1;
		          a333<=a33;
		          a444<=a44;
		          b333<=b33;
		          b444<=b44;

		          a555<=a55;
		          b555<=b55;

			  a666<=a66;
		          b666<=b66;
			  a777<=a77;
			  b777<=b77;


		        end

		always @ (posedge clk)
		        begin
		          s111<=s11;
		          s22<=s2;
			{c3,s3}<=a333+b333+c2;
		          a4444<=a444;
		          b4444<=b444;

		          a5555<=a555;
		          b5555<=b555;
			  a6666<=a666;
		          b6666<=b666;
			  a7777<=a777;
			  b7777<=b777;
		        end
		always @ (posedge clk)
		        begin
		          s1111<=s111;
		          s222<=s22;
		          s33<=s3;
		          {c4,s4}<=a4444+b4444+c3;

		          a55555<=a5555;
		          b55555<=b5555;
			  a66666<=a6666;
		          b66666<=b6666;
			  a77777<=a7777;
			  b77777<=b7777;


		        end

		     always @ (posedge clk)
		        begin
		          s11111<=s1111;
		          s2222<=s222;
		          s333<=s33;
		          s44<=s4;


		          {c5,s5}<=a55555+b55555+c4;
			
			  a666666<=a66666;
		          b666666<=b66666;
			  a777777<=a77777;
			  b777777<=b77777;



		        end


			 always @ (posedge clk)
					begin
					  s111111<=s11111;
					  s22222<=s2222;
		          		s3333<=s333;
		         		 s444<=s44;
					s55<=s5;
				{c6,s6}<=a666666+b666666+c5;
				
				a7777777<=a777777;
				b7777777<=b777777;
					  

					end
			
			always @ (posedge clk)
					begin
					  s1111111<=s111111;
					  s222222<=s22222;
		          		s33333<=s3333;
		         		 s4444<=s444;
					s555<=s55;
					s66<=s6;
				{cout,s7}<=a7777777+b7777777+c6;
					  
					end

			assign s={{s7[3:0]},{s66[3:0]},{s555[3:0]},{s4444[3:0]},{s33333[3:0]},{s222222[5:0]},{s1111111[5:0]}};

	endmodule

Vlsi/Behavrioural/ST1/fa32bit_tb.v
// Code your testbench here
// or browse Examples
module fa32bit_tb;
	parameter n = 32;
  	wire [n-1:0] s;//output
	wire [n-1:0] cout;//output
	reg [n-1:0] a,b;
	reg cin;//input
	reg clk;
	

	rtlfa32_4 inst(
      	.s(s),
		.cout(cout),
		.cin(cin),
		.a(a),
      	.b(b),
      	.clk(clk)
	);

initial begin
  $dumpfile("dump.vcd");
  $dumpvars(1);
	a = 32'b00000000000000000000000000000000;
	b = 32'b00000000000000000000000000000000;
  	clk = 0;
	cin = 0;
	end
	always #40 a = a+1;
	always #40 b = b+1;
  	always #0.5 clk = ~clk;
	//always #40 cin = ~cin;
	initial #500 $finish;
endmodule

Vlsi/Behavrioural/ST1/dump.vcd
$date
	Sun Jan  1 14:27:12 2023
$end
$version
	Icarus Verilog
$end
$timescale
	1s
$end
$scope module fa32bit_tb $end
$var wire 32 ! s [31:0] $end
$var wire 1 " cout $end
$var reg 32 # a [31:0] $end
$var reg 32 $ b [31:0] $end
$var reg 1 % cin $end
$var reg 1 & clk $end
$upscope $end
$enddefinitions $end
#0
$dumpvars
0&
0%
b0 $
b0 #
x"
bx !
$end
#1
1&
#2
0&
#3
1&
#4
0&
#5
1&
#6
0&
#7
1&
#8
0&
#9
1&
#10
0&
#11
1&
#12
0&
#13
1&
#14
0&
#15
0"
b0 !
1&
#16
0&
#17
1&
#18
0&
#19
1&
#20
0&
#21
1&
#22
0&
#23
1&
#24
0&
#25
1&
#26
0&
#27
1&
#28
0&
#29
1&
#30
0&
#31
1&
#32
0&
#33
1&
#34
0&
#35
1&
#36
0&
#37
1&
#38
0&
#39
1&
#40
0&
b1 $
b1 #
#41
1&
#42
0&
#43
1&
#44
0&
#45
1&
#46
0&
#47
1&
#48
0&
#49
1&
#50
0&
#51
1&
#52
0&
#53
1&
#54
0&
#55
b10 !
1&
#56
0&
#57
1&
#58
0&
#59
1&
#60
0&
#61
1&
#62
0&
#63
1&
#64
0&
#65
1&
#66
0&
#67
1&
#68
0&
#69
1&
#70
0&
#71
1&
#72
0&
#73
1&
#74
0&
#75
1&
#76
0&
#77
1&
#78
0&
#79
1&
#80
0&
b10 $
b10 #
#81
1&
#82
0&
#83
1&
#84
0&
#85
1&
#86
0&
#87
1&
#88
0&
#89
1&
#90
0&
#91
1&
#92
0&
#93
1&
#94
0&
#95
b100 !
1&
#96
0&
#97
1&
#98
0&
#99
1&
#100
0&
#101
1&
#102
0&
#103
1&
#104
0&
#105
1&
#106
0&
#107
1&
#108
0&
#109
1&
#110
0&
#111
1&
#112
0&
#113
1&
#114
0&
#115
1&
#116
0&
#117
1&
#118
0&
#119
1&
#120
0&
b11 $
b11 #
#121
1&
#122
0&
#123
1&
#124
0&
#125
1&
#126
0&
#127
1&
#128
0&
#129
1&
#130
0&
#131
1&
#132
0&
#133
1&
#134
0&
#135
b110 !
1&
#136
0&
#137
1&
#138
0&
#139
1&
#140
0&
#141
1&
#142
0&
#143
1&
#144
0&
#145
1&
#146
0&
#147
1&
#148
0&
#149
1&
#150
0&
#151
1&
#152
0&
#153
1&
#154
0&
#155
1&
#156
0&
#157
1&
#158
0&
#159
1&
#160
0&
b100 $
b100 #
#161
1&
#162
0&
#163
1&
#164
0&
#165
1&
#166
0&
#167
1&
#168
0&
#169
1&
#170
0&
#171
1&
#172
0&
#173
1&
#174
0&
#175
b1000 !
1&
#176
0&
#177
1&
#178
0&
#179
1&
#180
0&
#181
1&
#182
0&
#183
1&
#184
0&
#185
1&
#186
0&
#187
1&
#188
0&
#189
1&
#190
0&
#191
1&
#192
0&
#193
1&
#194
0&
#195
1&
#196
0&
#197
1&
#198
0&
#199
1&
#200
0&
b101 $
b101 #
#201
1&
#202
0&
#203
1&
#204
0&
#205
1&
#206
0&
#207
1&
#208
0&
#209
1&
#210
0&
#211
1&
#212
0&
#213
1&
#214
0&
#215
b1010 !
1&
#216
0&
#217
1&
#218
0&
#219
1&
#220
0&
#221
1&
#222
0&
#223
1&
#224
0&
#225
1&
#226
0&
#227
1&
#228
0&
#229
1&
#230
0&
#231
1&
#232
0&
#233
1&
#234
0&
#235
1&
#236
0&
#237
1&
#238
0&
#239
1&
#240
0&
b110 $
b110 #
#241
1&
#242
0&
#243
1&
#244
0&
#245
1&
#246
0&
#247
1&
#248
0&
#249
1&
#250
0&
#251
1&
#252
0&
#253
1&
#254
0&
#255
b1100 !
1&
#256
0&
#257
1&
#258
0&
#259
1&
#260
0&
#261
1&
#262
0&
#263
1&
#264
0&
#265
1&
#266
0&
#267
1&
#268
0&
#269
1&
#270
0&
#271
1&
#272
0&
#273
1&
#274
0&
#275
1&
#276
0&
#277
1&
#278
0&
#279
1&
#280
0&
b111 $
b111 #
#281
1&
#282
0&
#283
1&
#284
0&
#285
1&
#286
0&
#287
1&
#288
0&
#289
1&
#290
0&
#291
1&
#292
0&
#293
1&
#294
0&
#295
b1110 !
1&
#296
0&
#297
1&
#298
0&
#299
1&
#300
0&
#301
1&
#302
0&
#303
1&
#304
0&
#305
1&
#306
0&
#307
1&
#308
0&
#309
1&
#310
0&
#311
1&
#312
0&
#313
1&
#314
0&
#315
1&
#316
0&
#317
1&
#318
0&
#319
1&
#320
0&
b1000 $
b1000 #
#321
1&
#322
0&
#323
1&
#324
0&
#325
1&
#326
0&
#327
1&
#328
0&
#329
1&
#330
0&
#331
1&
#332
0&
#333
1&
#334
0&
#335
b10000 !
1&
#336
0&
#337
1&
#338
0&
#339
1&
#340
0&
#341
1&
#342
0&
#343
1&
#344
0&
#345
1&
#346
0&
#347
1&
#348
0&
#349
1&
#350
0&
#351
1&
#352
0&
#353
1&
#354
0&
#355
1&
#356
0&
#357
1&
#358
0&
#359
1&
#360
0&
b1001 $
b1001 #
#361
1&
#362
0&
#363
1&
#364
0&
#365
1&
#366
0&
#367
1&
#368
0&
#369
1&
#370
0&
#371
1&
#372
0&
#373
1&
#374
0&
#375
b10010 !
1&
#376
0&
#377
1&
#378
0&
#379
1&
#380
0&
#381
1&
#382
0&
#383
1&
#384
0&
#385
1&
#386
0&
#387
1&
#388
0&
#389
1&
#390
0&
#391
1&
#392
0&
#393
1&
#394
0&
#395
1&
#396
0&
#397
1&
#398
0&
#399
1&
#400
0&
b1010 $
b1010 #
#401
1&
#402
0&
#403
1&
#404
0&
#405
1&
#406
0&
#407
1&
#408
0&
#409
1&
#410
0&
#411
1&
#412
0&
#413
1&
#414
0&
#415
b10100 !
1&
#416
0&
#417
1&
#418
0&
#419
1&
#420
0&
#421
1&
#422
0&
#423
1&
#424
0&
#425
1&
#426
0&
#427
1&
#428
0&
#429
1&
#430
0&
#431
1&
#432
0&
#433
1&
#434
0&
#435
1&
#436
0&
#437
1&
#438
0&
#439
1&
#440
0&
b1011 $
b1011 #
#441
1&
#442
0&
#443
1&
#444
0&
#445
1&
#446
0&
#447
1&
#448
0&
#449
1&
#450
0&
#451
1&
#452
0&
#453
1&
#454
0&
#455
b10110 !
1&
#456
0&
#457
1&
#458
0&
#459
1&
#460
0&
#461
1&
#462
0&
#463
1&
#464
0&
#465
1&
#466
0&
#467
1&
#468
0&
#469
1&
#470
0&
#471
1&
#472
0&
#473
1&
#474
0&
#475
1&
#476
0&
#477
1&
#478
0&
#479
1&
#480
0&
b1100 $
b1100 #
#481
1&
#482
0&
#483
1&
#484
0&
#485
1&
#486
0&
#487
1&
#488
0&
#489
1&
#490
0&
#491
1&
#492
0&
#493
1&
#494
0&
#495
b11000 !
1&
